pytest_django_casperjs/helper.py
pytest_django_casperjs/__init__.py
pytest_django_casperjs/plugin.py
pytest_django_casperjs/fixtures.py
pytest_django_casperjs/compat.py
pytest_django_casperjs/tests/__init__.py
pytest_django_casperjs/tests/urls_liveserver.py
pytest_django_casperjs/tests/test_fixtures.py
pytest_django_casperjs/tests/helpers.py
pytest_django_casperjs/tests/settings.py
pytest_django_casperjs/tests/app/__init__.py
pytest_django_casperjs/tests/app/models.py
pytest_django_casperjs-0.1.0.dist-info/metadata.json
pytest_django_casperjs-0.1.0.dist-info/entry_points.txt
pytest_django_casperjs-0.1.0.dist-info/LICENSE.txt
pytest_django_casperjs-0.1.0.dist-info/RECORD
pytest_django_casperjs-0.1.0.dist-info/DESCRIPTION.rst
pytest_django_casperjs-0.1.0.dist-info/top_level.txt
pytest_django_casperjs-0.1.0.dist-info/WHEEL
pytest_django_casperjs-0.1.0.dist-info/METADATA
